{
  "weapon_type": "SWORD",
  "rarity": "COMMON",
  "attack_damage": {
    "min": 10,
    "max": 40
  },
  "attack_speed": {
    "min": 1.48,
    "max": 2
  },
  "critical_chance": {
    "min": 0,
    "max": 0
  },
  "critical_damage": {
    "min": 2,
    "max": 2
  },
  "durability": {
    "min": 175,
    "max": 325
  },
  "status_chance": {
    "min": 100,
    "max": 100
  },
  "enchantability": {
    "min": 14,
    "max": 14
  },
  "range": {
    "min": 4,
    "max": 4
  },
  "is_ranged": "false",
  "secondarydata": [],
  "properties": [
    "aeonspast:versatile",
    "aeonspast:sweeping",
    "aeonspast:kinetic",
    "aeonspast:brutal"
  ],
  "spells": [
    "aeonspast:true_strike",
    "aeonspast:double_slash",
    "aeonspast:cleave"
  ]
}